svgl/__init__.py
svgl/settings.py
svgl/svgl.py
svgl-0.1.8.dist-info/LICENSE
svgl-0.1.8.dist-info/METADATA
svgl-0.1.8.dist-info/WHEEL
svgl-0.1.8.dist-info/top_level.txt
svgl-0.1.8.dist-info/RECORD
