Metadata-Version: 2.2
Name: svgl
Version: 0.1.8
Summary: Interact with the https://svgl.app/.
Home-page: https://github.com/tsnaketech/svgl
Author: SnakeTech
Author-email: repo@snaketech.net
License: MIT
Project-URL: Source, https://github.com/tsnaketech/svgl
Project-URL: Issues, https://github.com/tsnaketech/svgl/issues
Classifier: Intended Audience :: Developers
Classifier: License :: OSI Approved :: MIT License
Classifier: Natural Language :: English
Classifier: Natural Language :: French
Classifier: Programming Language :: Python :: 3.11
Classifier: Programming Language :: Python :: 3.12
License-File: LICENSE
Requires-Dist: httpx
Requires-Dist: pydantic
Dynamic: author
Dynamic: author-email
Dynamic: classifier
Dynamic: description
Dynamic: description-content-type
Dynamic: home-page
Dynamic: license
Dynamic: project-url
Dynamic: requires-dist
Dynamic: summary
